odoo/addons/product_bom_revision/README.rst
odoo/addons/product_bom_revision/__init__.py
odoo/addons/product_bom_revision/__manifest__.py
odoo/addons/product_bom_revision/i18n/es.po
odoo/addons/product_bom_revision/i18n/product_bom_revision.pot
odoo/addons/product_bom_revision/i18n/pt.po
odoo/addons/product_bom_revision/models/__init__.py
odoo/addons/product_bom_revision/models/mrp.py
odoo/addons/product_bom_revision/models/product.py
odoo/addons/product_bom_revision/readme/CONTRIBUTORS.rst
odoo/addons/product_bom_revision/readme/DESCRIPTION.rst
odoo/addons/product_bom_revision/readme/USAGE.rst
odoo/addons/product_bom_revision/static/description/icon.png
odoo/addons/product_bom_revision/static/description/index.html
odoo/addons/product_bom_revision/views/mrp_view.xml
odoo/addons/product_bom_revision/views/product_view.xml
odoo12_addon_product_bom_revision-12.0.1.0.2.dist-info/METADATA
odoo12_addon_product_bom_revision-12.0.1.0.2.dist-info/WHEEL
odoo12_addon_product_bom_revision-12.0.1.0.2.dist-info/top_level.txt
odoo12_addon_product_bom_revision-12.0.1.0.2.dist-info/RECORD
