Metadata-Version: 2.1
Name: odoo12-addon-product-bom-revision
Version: 12.0.1.0.2
Summary: Store the revision of a product and a BOM
Home-page: https://github.com/OCA/product-attribute
Author: C2i Change 2 improve,Odoo Community Association (OCA)
Author-email: support@odoo-community.org
License: AGPL-3
Platform: UNKNOWN
Classifier: Programming Language :: Python
Classifier: Framework :: Odoo
Classifier: License :: OSI Approved :: GNU Affero General Public License v3
Requires-Python: >=3.5
Requires-Dist: odoo (<12.1dev,>=12.0a)
